code_context_analyzer/__init__.py
code_context_analyzer/main.py
code_context_analyzer/analyzer/__init__.py
code_context_analyzer/analyzer/clipboard.py
code_context_analyzer/analyzer/discovery.py
code_context_analyzer/analyzer/parsers/__init__.py
code_context_analyzer/analyzer/parsers/base.py
code_context_analyzer/analyzer/parsers/js_parser.py
code_context_analyzer/analyzer/parsers/python_parser.py
code_context_analyzer/cli/__init__.py
code_context_analyzer/dto/__init__.py
code_context_analyzer/dto/models.py
code_context_analyzer/formatters/__init__.py
code_context_analyzer/formatters/base.py
code_context_analyzer/formatters/default.py
code_context_analyzer/formatters/factory.py
code_context_analyzer/formatters/html_formatter.py
code_context_analyzer/formatters/json_formatter.py
code_context_analyzer/formatters/yaml_formatter.py
code_context_analyzer/repo_system/__init__.py
code_context_analyzer/repo_system/handler.py
code_context_analyzer/repo_system/session.py
code_context_analyzer/tests/__init__.py
code_context_analyzer/tests/test_cli.py
code_context_analyzer/tests/test_discovery.py
code_context_analyzer/tests/test_formatter.py
code_context_analyzer/tests/test_repository_handler.py
code_context_analyzer/tests/test_parsers/__init__.py
code_context_analyzer/tests/test_parsers/test_js_parser.py
code_context_analyzer/tests/test_parsers/test_python_parser.py
code_context_analyzer/utils/__init__.py
code_context_analyzer/utils/dto_converter.py
code_context_analyzer/utils/temp_dir.py
code_context_analyzer-0.3.3.dist-info/licenses/LICENSE.md
code_context_analyzer-0.3.3.dist-info/METADATA
code_context_analyzer-0.3.3.dist-info/WHEEL
code_context_analyzer-0.3.3.dist-info/entry_points.txt
code_context_analyzer-0.3.3.dist-info/top_level.txt
code_context_analyzer-0.3.3.dist-info/RECORD
