Metadata-Version: 2.4
Name: code-context-analyzer
Version: 0.3.3
Summary: A tool to analyze codebase structure and summarize content to use with AI easily.
Home-page: https://github.com/ahasanular/code-context-analyzer
Author: Md. Ahasanul Arafath
Author-email: "Md. Ahasanul Arafath" <ahasanular@gmail.com>
License: MIT
Requires-Python: >=3.10
License-File: LICENSE.md
Requires-Dist: pyperclip>=1.9.0
Requires-Dist: PyYAML>=6.0.2
Dynamic: license-file
